flashcards_cli/__init__.py
flashcards_cli/__main__.py
flashcards_cli/card_set.py
flashcards_cli/flashcard.py
flashcards_cli-1.3.8.dist-info/LICENSE
flashcards_cli-1.3.8.dist-info/METADATA
flashcards_cli-1.3.8.dist-info/WHEEL
flashcards_cli-1.3.8.dist-info/entry_points.txt
flashcards_cli-1.3.8.dist-info/top_level.txt
flashcards_cli-1.3.8.dist-info/RECORD
