Metadata-Version: 2.1
Name: flashcards-cli
Version: 1.3.8
Summary: Learn a set of flashcards
Home-page: https://github.com/jj-style/flashcards-cli
Author: JJ Style
Author-email: style.jj@protonmail.com
License: GNU General Public License v3 (GPLv3)
Platform: UNKNOWN
Classifier: License :: OSI Approved :: GNU General Public License v3 (GPLv3)
Classifier: Programming Language :: Python :: 3
Classifier: Programming Language :: Python :: 3.6
